.coveragerc
.gitignore
.isort.cfg
.pre-commit-config.yaml
.travis.yml
AUTHORS.rst
CHANGELOG.rst
LICENSE.txt
Makefile
README.rst
pyproject.toml
requirements.txt
setup.cfg
setup.py
tox.ini
docs/Makefile
docs/authors.rst
docs/changelog.rst
docs/conf.py
docs/index.rst
docs/license.rst
docs/_static/.gitignore
src/metapack_github/__init__.py
src/metapack_github/cli.py
src/metapack_github.egg-info/PKG-INFO
src/metapack_github.egg-info/SOURCES.txt
src/metapack_github.egg-info/dependency_links.txt
src/metapack_github.egg-info/entry_points.txt
src/metapack_github.egg-info/not-zip-safe
src/metapack_github.egg-info/requires.txt
src/metapack_github.egg-info/top_level.txt
tests/conftest.py
tests/test_skeleton.py
tests/travis_install.sh