Metadata-Version: 2.1
Name: metapack-github
Version: 0.0.5
Summary: Linked data support for Metapack data packages
Home-page: https://pyscaffold.org/
Author: Eric Busboom
Author-email: eric@civicknowledge.com
License: mit
Platform: any
Classifier: Development Status :: 4 - Beta
Classifier: Programming Language :: Python
Requires-Python: >=3.6
Provides-Extra: testing
